napari_cryoet_data_portal/__init__.py
napari_cryoet_data_portal/_filter.py
napari_cryoet_data_portal/_listing_tree_widget.py
napari_cryoet_data_portal/_listing_widget.py
napari_cryoet_data_portal/_logging.py
napari_cryoet_data_portal/_metadata_widget.py
napari_cryoet_data_portal/_open_widget.py
napari_cryoet_data_portal/_progress_widget.py
napari_cryoet_data_portal/_reader.py
napari_cryoet_data_portal/_sample_data.py
napari_cryoet_data_portal/_task_worker.py
napari_cryoet_data_portal/_uri_widget.py
napari_cryoet_data_portal/_version.py
napari_cryoet_data_portal/_widget.py
napari_cryoet_data_portal/napari.yaml
napari_cryoet_data_portal/_tests/__init__.py
napari_cryoet_data_portal/_tests/_utils.py
napari_cryoet_data_portal/_tests/conftest.py
napari_cryoet_data_portal/_tests/test_listing_widget.py
napari_cryoet_data_portal/_tests/test_metadata_widget.py
napari_cryoet_data_portal/_tests/test_open_widget.py
napari_cryoet_data_portal/_tests/test_reader.py
napari_cryoet_data_portal/_tests/test_sample.py
napari_cryoet_data_portal/_tests/test_uri_widget.py
napari_cryoet_data_portal/_tests/test_widget.py
napari_cryoet_data_portal/_vendored/__init__.py
napari_cryoet_data_portal/_vendored/superqt/__init__.py
napari_cryoet_data_portal/_vendored/superqt/_searchable_tree_widget.py
napari_cryoet_data_portal-0.5.0.dist-info/LICENSE
napari_cryoet_data_portal-0.5.0.dist-info/METADATA
napari_cryoet_data_portal-0.5.0.dist-info/WHEEL
napari_cryoet_data_portal-0.5.0.dist-info/entry_points.txt
napari_cryoet_data_portal-0.5.0.dist-info/top_level.txt
napari_cryoet_data_portal-0.5.0.dist-info/RECORD
