Metadata-Version: 2.1
Name: napari-cryoet-data-portal
Version: 0.5.0
Summary: List, preview, and open data from the CZII CryoET Data Portal
Home-page: https://github.com/chanzuckerberg/napari-cryoet-data-portal
Author: Andy Sweet
Author-email: andrewdsweet@gmail.com
License: MIT
Project-URL: Bug Tracker, https://github.com/chanzuckerberg/napari-cryoet-data-portal/issues
Project-URL: Documentation, https://github.com/chanzuckerberg/napari-cryoet-data-portal#README.md
Project-URL: Source Code, https://github.com/chanzuckerberg/napari-cryoet-data-portal
Project-URL: User Support, https://github.com/chanzuckerberg/napari-cryoet-data-portal/issues
Classifier: Development Status :: 4 - Beta
Classifier: Framework :: napari
Classifier: Intended Audience :: Developers
Classifier: License :: OSI Approved :: MIT License
Classifier: Operating System :: OS Independent
Classifier: Programming Language :: Python
Classifier: Programming Language :: Python :: 3
Classifier: Programming Language :: Python :: 3 :: Only
Classifier: Programming Language :: Python :: 3.8
Classifier: Programming Language :: Python :: 3.9
Classifier: Programming Language :: Python :: 3.10
Classifier: Topic :: Scientific/Engineering :: Image Processing
Requires-Python: >=3.8
License-File: LICENSE
Requires-Dist: cmap
Requires-Dist: cryoet_data_portal~=4.0
Requires-Dist: fsspec[http,s3]
Requires-Dist: npe2
Requires-Dist: numpy
Requires-Dist: napari>=0.4.19
Requires-Dist: napari_ome_zarr
Requires-Dist: ndjson
Requires-Dist: qtpy
Requires-Dist: superqt
Provides-Extra: testing
Requires-Dist: tox; extra == "testing"
Requires-Dist: pytest; extra == "testing"
Requires-Dist: pytest-cov; extra == "testing"
Requires-Dist: pytest-mock; extra == "testing"
Requires-Dist: pytest-qt; extra == "testing"
Requires-Dist: napari; extra == "testing"
Requires-Dist: pyqt5; extra == "testing"
